eventgraphs/__init__.py
eventgraphs/analysis.py
eventgraphs/centrality.py
eventgraphs/clustering.py
eventgraphs/eventgraph.py
eventgraphs/motif.py
eventgraphs/plotting.py
eventgraphs/prebuilt.py
eventgraphs-0.1.dist-info/DESCRIPTION.rst
eventgraphs-0.1.dist-info/METADATA
eventgraphs-0.1.dist-info/RECORD
eventgraphs-0.1.dist-info/WHEEL
eventgraphs-0.1.dist-info/metadata.json
eventgraphs-0.1.dist-info/top_level.txt
