Metadata-Version: 2.0
Name: eventgraphs
Version: 0.1
Summary: Creating event graphs from temporal network event sequence data (clickstreams, messages, contacts,
Home-page: UNKNOWN
Author: Andrew Mellor
Author-email: mellor91@hotmail.co.uk
License: Apache Software License
Keywords: temporal motifs networks events clickstreams higher-order
Platform: UNKNOWN
Classifier: Programming Language :: Python :: 3
Classifier: Programming Language :: Python :: 3.2
Classifier: Programming Language :: Python :: 3.3
Classifier: Programming Language :: Python :: 3.4
Classifier: Programming Language :: Python :: 3.5
Classifier: Programming Language :: Python :: 3.6
Classifier: Development Status :: 3 - Alpha
Classifier: License :: OSI Approved :: Apache Software License
Classifier: Topic :: Scientific/Engineering
Classifier: Intended Audience :: Science/Research
Requires-Python: >=3
Requires-Dist: ipython
Requires-Dist: matplotlib
Requires-Dist: networkx
Requires-Dist: numpy
Requires-Dist: pandas
Requires-Dist: scipy
